MANIFEST.in
README.rst
setup.py
collective/__init__.py
collective.regjsonify.egg-info/PKG-INFO
collective.regjsonify.egg-info/SOURCES.txt
collective.regjsonify.egg-info/dependency_links.txt
collective.regjsonify.egg-info/entry_points.txt
collective.regjsonify.egg-info/namespace_packages.txt
collective.regjsonify.egg-info/not-zip-safe
collective.regjsonify.egg-info/requires.txt
collective.regjsonify.egg-info/top_level.txt
collective/regjsonify/__init__.py
collective/regjsonify/configure.zcml
collective/regjsonify/fields.py
collective/regjsonify/interfaces.py
collective/regjsonify/jsonify.py
collective/regjsonify/testing.py
collective/regjsonify/tests.py
docs/HISTORY.rst
docs/INSTALL.txt
docs/LICENSE.GPL
docs/LICENSE.txt