Metadata-Version: 1.0
Name: collective.regjsonify
Version: 0.2.0
Summary: Export Plone registry content to a JSON compatible Python structure
Home-page: http://github.com/keul/collective.regjsonify
Author: keul
Author-email: luca@keul.it
License: GPL
Keywords: plone registry json export
Platform: UNKNOWN
Classifier: Framework :: Plone
Classifier: Framework :: Zope3
Classifier: Intended Audience :: Developers
Classifier: Programming Language :: Python
Classifier: License :: OSI Approved :: GNU General Public License (GPL)
